[
    {
        "inputs": [],
        "stateMutability": "nonpayable",
        "type": "constructor"
    },
    {
        "anonymous": false,
        "inputs": [
            {
                "indexed": true,
                "internalType": "address",
                "name": "userAddress",
                "type": "address"
            },
            {
                "indexed": false,
                "internalType": "uint256",
                "name": "fightId",
                "type": "uint256"
            },
            {
                "indexed": false,
                "internalType": "uint256",
                "name": "rewardAmount",
                "type": "uint256"
            },
            {
                "indexed": false,
                "internalType": "uint256",
                "name": "timestamp",
                "type": "uint256"
            }
        ],
        "name": "ClaimReward",
        "type": "event"
    },
    {
        "anonymous": false,
        "inputs": [
            {
                "indexed": true,
                "internalType": "address",
                "name": "previousOwner",
                "type": "address"
            },
            {
                "indexed": true,
                "internalType": "address",
                "name": "newOwner",
                "type": "address"
            }
        ],
        "name": "OwnershipTransferred",
        "type": "event"
    },
    {
        "anonymous": false,
        "inputs": [
            {
                "indexed": true,
                "internalType": "address",
                "name": "userAddress",
                "type": "address"
            },
            {
                "indexed": false,
                "internalType": "uint256",
                "name": "fightId",
                "type": "uint256"
            },
            {
                "indexed": false,
                "internalType": "uint256",
                "name": "returnAmount",
                "type": "uint256"
            },
            {
                "indexed": false,
                "internalType": "uint256",
                "name": "timestamp",
                "type": "uint256"
            }
        ],
        "name": "ReturnBet",
        "type": "event"
    },
    {
        "inputs": [],
        "name": "addressManagerAddress",
        "outputs": [
            {
                "internalType": "address",
                "name": "",
                "type": "address"
            }
        ],
        "stateMutability": "view",
        "type": "function"
    },
    {
        "inputs": [
            {
                "internalType": "uint256",
                "name": "fightId",
                "type": "uint256"
            },
            {
                "internalType": "uint256",
                "name": "betStakeId",
                "type": "uint256"
            },
            {
                "internalType": "uint256",
                "name": "amountToken",
                "type": "uint256"
            }
        ],
        "name": "betOnFight",
        "outputs": [],
        "stateMutability": "nonpayable",
        "type": "function"
    },
    {
        "inputs": [
            {
                "internalType": "uint256",
                "name": "fightId",
                "type": "uint256"
            },
            {
                "internalType": "address",
                "name": "account",
                "type": "address"
            }
        ],
        "name": "checkReward",
        "outputs": [
            {
                "internalType": "uint256",
                "name": "",
                "type": "uint256"
            }
        ],
        "stateMutability": "view",
        "type": "function"
    },
    {
        "inputs": [
            {
                "internalType": "uint256",
                "name": "fightId",
                "type": "uint256"
            }
        ],
        "name": "claimReward",
        "outputs": [],
        "stateMutability": "nonpayable",
        "type": "function"
    },
    {
        "inputs": [
            {
                "internalType": "uint256",
                "name": "fightId",
                "type": "uint256"
            }
        ],
        "name": "getBetStats",
        "outputs": [
            {
                "internalType": "uint256",
                "name": "",
                "type": "uint256"
            },
            {
                "internalType": "uint256",
                "name": "",
                "type": "uint256"
            },
            {
                "internalType": "uint256",
                "name": "",
                "type": "uint256"
            },
            {
                "internalType": "uint256",
                "name": "",
                "type": "uint256"
            }
        ],
        "stateMutability": "view",
        "type": "function"
    },
    {
        "inputs": [],
        "name": "owner",
        "outputs": [
            {
                "internalType": "address",
                "name": "",
                "type": "address"
            }
        ],
        "stateMutability": "view",
        "type": "function"
    },
    {
        "inputs": [],
        "name": "renounceOwnership",
        "outputs": [],
        "stateMutability": "nonpayable",
        "type": "function"
    },
    {
        "inputs": [
            {
                "internalType": "uint256",
                "name": "fightId",
                "type": "uint256"
            }
        ],
        "name": "returnCanceledFightBet",
        "outputs": [],
        "stateMutability": "nonpayable",
        "type": "function"
    },
    {
        "inputs": [
            {
                "internalType": "address",
                "name": "_addressManagerAddress",
                "type": "address"
            }
        ],
        "name": "setAddressManager",
        "outputs": [],
        "stateMutability": "nonpayable",
        "type": "function"
    },
    {
        "inputs": [
            {
                "internalType": "uint8",
                "name": "FEE",
                "type": "uint8"
            }
        ],
        "name": "setSettings",
        "outputs": [
            {
                "components": [
                    {
                        "internalType": "uint8",
                        "name": "_FEE",
                        "type": "uint8"
                    }
                ],
                "internalType": "struct Roosters_Bets.Settings",
                "name": "",
                "type": "tuple"
            }
        ],
        "stateMutability": "nonpayable",
        "type": "function"
    },
    {
        "inputs": [
            {
                "internalType": "address",
                "name": "newOwner",
                "type": "address"
            }
        ],
        "name": "transferOwnership",
        "outputs": [],
        "stateMutability": "nonpayable",
        "type": "function"
    }
]